fshredder/__init__.py
fshredder/fshredder.py
fshredder-0.1.0.dist-info/LICENSE
fshredder-0.1.0.dist-info/METADATA
fshredder-0.1.0.dist-info/WHEEL
fshredder-0.1.0.dist-info/entry_points.txt
fshredder-0.1.0.dist-info/top_level.txt
fshredder-0.1.0.dist-info/RECORD
