Metadata-Version: 2.1
Name: fshredder
Version: 0.1.0
Summary: Advanced file shredding tool that deletes files with no data left using encryption techniques
Home-page: https://github.com/babaralijamali/fshredder
Author: Babar Ali Jamali
Author-email: babar995@gmail.com
Classifier: Programming Language :: Python :: 3
Classifier: License :: OSI Approved :: MIT License
Classifier: Operating System :: OS Independent
Requires-Python: >=3.6
License-File: LICENSE
